{"title":"Red.On.The.Head.Fire.In.The.Bed.5.XXX.DVDRip.x264-TwistedDesires","uid":13144837,"size":1439226449,"categoryP":"porn","categoryS":"movies","magnet":"?xt=urn:btih:008973ccb71641716d7e472800ae38d3a4ac09ea&amp;dn=Red.On.The.Head.Fire.In.The.Bed.5.XXX.DVDRip.x264-TwistedDesires&amp;tr=udp%3A%2F%2Ftracker.leechers-paradise.org%3A6969&amp;tr=udp%3A%2F%2Fzer0day.ch%3A1337&amp;tr=udp%3A%2F%2Fopen.demonii.com%3A1337&amp;tr=udp%3A%2F%2Ftracker.coppersurfer.tk%3A6969&amp;tr=udp%3A%2F%2Fexodus.desync.com%3A6969","seeders":1,"leechers":0,"uploader":"Borusssia","files":4,"time":1452016391,"description":"Screens\r\n \nhttp://www.imagesnake.org/show/69297/1.jpg \r\n \nhttp://www.imagesnake.org/show/69298/front.jpg","torrent":{"xt":"urn:btih:008973ccb71641716d7e472800ae38d3a4ac09ea","amp;dn":"Red.On.The.Head.Fire.In.The.Bed.5.XXX.DVDRip.x264-TwistedDesires","amp;tr":["udp%3A%2F%2Ftracker.leechers-paradise.org%3A6969","udp%3A%2F%2Fzer0day.ch%3A1337","udp%3A%2F%2Fopen.demonii.com%3A1337","udp%3A%2F%2Ftracker.coppersurfer.tk%3A6969","udp%3A%2F%2Fexodus.desync.com%3A6969"],"infoHash":"008973ccb71641716d7e472800ae38d3a4ac09ea","infoHashBuffer":{"type":"Buffer","data":[0,137,115,204,183,22,65,113,109,126,71,40,0,174,56,211,164,172,9,234]},"announce":[],"urlList":[]}}