{"title":"Real Escort 19yr Sassy Sam","uid":9912323,"size":888498113,"categoryP":"porn","categoryS":"movie_clips","magnet":"?xt=urn:btih:06d131a5a73600c16c1575e5c37f6d1adcba0fa9&amp;dn=Real+Escort+19yr+Sassy+Sam&amp;tr=udp%3A%2F%2Ftracker.openbittorrent.com%3A80&amp;tr=udp%3A%2F%2Fopen.demonii.com%3A1337&amp;tr=udp%3A%2F%2Ftracker.coppersurfer.tk%3A6969&amp;tr=udp%3A%2F%2Fexodus.desync.com%3A6969","seeders":1,"leechers":0,"uploader":null,"files":13,"time":1396913407,"description":" &lt;a href=&quot;http://s12.postimg.org/7jkiaqa19/screens_Sassy_Sam.jpg&quot; rel=&quot;nofollow&quot; target=&quot;_NEW&quot;&gt;http://s12.postimg.org/7jkiaqa19/screens_Sassy_Sam.jpg&lt;/a&gt;","torrent":{"xt":"urn:btih:06d131a5a73600c16c1575e5c37f6d1adcba0fa9","amp;dn":"Real+Escort+19yr+Sassy+Sam","amp;tr":["udp%3A%2F%2Ftracker.openbittorrent.com%3A80","udp%3A%2F%2Fopen.demonii.com%3A1337","udp%3A%2F%2Ftracker.coppersurfer.tk%3A6969","udp%3A%2F%2Fexodus.desync.com%3A6969"],"infoHash":"06d131a5a73600c16c1575e5c37f6d1adcba0fa9","infoHashBuffer":{"type":"Buffer","data":[6,209,49,165,167,54,0,193,108,21,117,229,195,127,109,26,220,186,15,169]},"announce":[],"urlList":[]}}