{"title":"Mysteries at the Museum S07E06 HDTV x264-SPASM","uid":11280894,"size":236100054,"categoryP":"video","categoryS":"tv_shows","magnet":"?xt=urn:btih:1afee0291fc61d9c1867851d1fd559e854be467e&amp;dn=Mysteries+at+the+Museum+S07E06+HDTV+x264-SPASM&amp;tr=udp%3A%2F%2Ftracker.openbittorrent.com%3A80&amp;tr=udp%3A%2F%2Fopen.demonii.com%3A1337&amp;tr=udp%3A%2F%2Ftracker.coppersurfer.tk%3A6969&amp;tr=udp%3A%2F%2Fexodus.desync.com%3A6969","seeders":2,"leechers":0,"uploader":"LegendET","files":2,"time":1414212353,"description":"Video\nFormat: AVC\nWidth: 720 pixels\nHeight: 404 pixels\nAudio\nFormat: AAC\nBit rate: Variable\nSource: 720p DHD","torrent":{"xt":"urn:btih:1afee0291fc61d9c1867851d1fd559e854be467e","amp;dn":"Mysteries+at+the+Museum+S07E06+HDTV+x264-SPASM","amp;tr":["udp%3A%2F%2Ftracker.openbittorrent.com%3A80","udp%3A%2F%2Fopen.demonii.com%3A1337","udp%3A%2F%2Ftracker.coppersurfer.tk%3A6969","udp%3A%2F%2Fexodus.desync.com%3A6969"],"infoHash":"1afee0291fc61d9c1867851d1fd559e854be467e","infoHashBuffer":{"type":"Buffer","data":[26,254,224,41,31,198,29,156,24,103,133,29,31,213,89,232,84,190,70,126]},"announce":[],"urlList":[]}}