{"title":"Kat May - Beyond the North Wind (2014)","uid":11424007,"size":214360127,"categoryP":"audio","categoryS":"music","magnet":"?xt=urn:btih:211ce7f81dd2836db51cf9fddd7623cb78f3c508&amp;dn=Kat+May+-+Beyond+the+North+Wind+%282014%29&amp;tr=udp%3A%2F%2Ftracker.openbittorrent.com%3A80&amp;tr=udp%3A%2F%2Fopen.demonii.com%3A1337&amp;tr=udp%3A%2F%2Ftracker.coppersurfer.tk%3A6969&amp;tr=udp%3A%2F%2Fexodus.desync.com%3A6969","seeders":1,"leechers":0,"uploader":"santicaz","files":11,"time":1415643133,"description":"Artist: Kat May\nTitle Of Album: Beyond the North Wind\nYear Of Release: 2014\nLabel: Self Released\nGenre: Indie Pop, Indie Folk\nQuality: FLAC\nTotal Time: 38:07 min\nTotal Size: 204 MB\n\n\nTracklist:\n\n1. Chicken Fried\n2. Whatever It Is\n3. Toes\n4. Free\n5. Highway 20 Ride\n6. As She's Walking Away (feat. Alan Jackson)\n7. Colder Weather\n8. Knee Deep (feat. Jimmy Buffett)\n9. Keep Me In Mind\n10. No Hurry\n11. The Wind\n12. Jump Right In\n13. Goodbye In Her Eyes\n14. Sweet Annie","torrent":{"xt":"urn:btih:211ce7f81dd2836db51cf9fddd7623cb78f3c508","amp;dn":"Kat+May+-+Beyond+the+North+Wind+%282014%29","amp;tr":["udp%3A%2F%2Ftracker.openbittorrent.com%3A80","udp%3A%2F%2Fopen.demonii.com%3A1337","udp%3A%2F%2Ftracker.coppersurfer.tk%3A6969","udp%3A%2F%2Fexodus.desync.com%3A6969"],"infoHash":"211ce7f81dd2836db51cf9fddd7623cb78f3c508","infoHashBuffer":{"type":"Buffer","data":[33,28,231,248,29,210,131,109,181,28,249,253,221,118,35,203,120,243,197,8]},"announce":[],"urlList":[]}}