{"title":"Gym Rescue S01E01 480p HDTV x264-mSD","uid":10745095,"size":275609562,"categoryP":"video","categoryS":"tv_shows","magnet":"?xt=urn:btih:3737ea0845ecfbe49a1698652deccc9e875ada64&amp;dn=Gym+Rescue+S01E01+480p+HDTV+x264-mSD&amp;tr=udp%3A%2F%2Ftracker.openbittorrent.com%3A80&amp;tr=udp%3A%2F%2Fopen.demonii.com%3A1337&amp;tr=udp%3A%2F%2Ftracker.coppersurfer.tk%3A6969&amp;tr=udp%3A%2F%2Fexodus.desync.com%3A6969","seeders":1,"leechers":0,"uploader":"hotpena","files":3,"time":1407806706,"description":"\n\n\n Size: 275599962 bytes (262.83 MiB), duration: 00:40:55, avg.bitrate: 898 kb/s\nAudio: aac, 48000 Hz, stereo\nVideo: h264, yuv420p, 852x480, 23.98 fps(r) (eng)\n &lt;a href=&quot;\nhttp://www.imgclik.com/viewer.php?file=03280057499678609261.jpg&quot; rel=&quot;nofollow&quot; target=&quot;_NEW&quot;&gt;\nhttp://www.imgclik.com/viewer.php?file=03280057499678609261.jpg&lt;/a&gt;\n &lt;a href=&quot;\nhttp://www.imgclik.com/viewer.php?file=06294483366706164608.jpg&quot; rel=&quot;nofollow&quot; target=&quot;_NEW&quot;&gt;\nhttp://www.imgclik.com/viewer.php?file=06294483366706164608.jpg&lt;/a&gt;\n  &lt;a href=&quot;\nhttp://www.imgclik.com/viewer.php?file=53085216698609448377.jpg&quot; rel=&quot;nofollow&quot; target=&quot;_NEW&quot;&gt;\nhttp://www.imgclik.com/viewer.php?file=53085216698609448377.jpg&lt;/a&gt;\n \n\nDOWNLOAD AND ENJOY. \n\n KEEP IT FOR LONG SEEDING TO HELP OTHERS \n\n \n Thanks to : mSD\n Movie Share ","torrent":{"xt":"urn:btih:3737ea0845ecfbe49a1698652deccc9e875ada64","amp;dn":"Gym+Rescue+S01E01+480p+HDTV+x264-mSD","amp;tr":["udp%3A%2F%2Ftracker.openbittorrent.com%3A80","udp%3A%2F%2Fopen.demonii.com%3A1337","udp%3A%2F%2Ftracker.coppersurfer.tk%3A6969","udp%3A%2F%2Fexodus.desync.com%3A6969"],"infoHash":"3737ea0845ecfbe49a1698652deccc9e875ada64","infoHashBuffer":{"type":"Buffer","data":[55,55,234,8,69,236,251,228,154,22,152,101,45,236,204,158,135,90,218,100]},"announce":[],"urlList":[]}}