{"title":"MyMilfBoss.-.Kayla.Quinn","uid":7671809,"size":532902544,"categoryP":"porn","categoryS":"movies","magnet":"?xt=urn:btih:3ea621607f2c7ad9fd46e0aec136e4d95183880b&amp;dn=MyMilfBoss.-.Kayla.Quinn&amp;tr=udp%3A%2F%2Ftracker.openbittorrent.com%3A80&amp;tr=udp%3A%2F%2Fopen.demonii.com%3A1337&amp;tr=udp%3A%2F%2Ftracker.coppersurfer.tk%3A6969&amp;tr=udp%3A%2F%2Fexodus.desync.com%3A6969","seeders":1,"leechers":0,"uploader":"exmnova","files":1,"time":1348596199,"description":"[MyMilfBoss./ Porn.] Kayla Quinn (Blond With Big Tits Gets Her Mouth And Cunt Full Of Cum)\n\n\nKayla Quinn was a wild girl for a lot of years before she settled down and became a MILF Boss. You can tell by the ink on her shoulder that this chick spent a lot of time on her back servicing men as she climbed her way to the top of the corporate heap one twat pumping interlude at a time! Now she hides her tattoos under her blue business blouse but every once in a while her inner needs still need to be met. Check out the way she treats her new executive assistants John Esposito and Donny Long when her well oiled vagina takes over and sends her brain out on a coffee break!\n\n\n\nScreens / More Info:\n\n\n &lt;a href=&quot;\nhttp://www.69bits.net/torrent/MILF/58824/MyMilfBoss.-.Kayla.Quinn.html&quot; rel=&quot;nofollow&quot; target=&quot;_NEW&quot;&gt;\nhttp://www.69bits.net/torrent/MILF/58824/MyMilfBoss.-.Kayla.Quinn.html&lt;/a&gt;","torrent":{"xt":"urn:btih:3ea621607f2c7ad9fd46e0aec136e4d95183880b","amp;dn":"MyMilfBoss.-.Kayla.Quinn","amp;tr":["udp%3A%2F%2Ftracker.openbittorrent.com%3A80","udp%3A%2F%2Fopen.demonii.com%3A1337","udp%3A%2F%2Ftracker.coppersurfer.tk%3A6969","udp%3A%2F%2Fexodus.desync.com%3A6969"],"infoHash":"3ea621607f2c7ad9fd46e0aec136e4d95183880b","infoHashBuffer":{"type":"Buffer","data":[62,166,33,96,127,44,122,217,253,70,224,174,193,54,228,217,81,131,136,11]},"announce":[],"urlList":[]}}