{"title":"Marches in HI-FI - Fiedler, Boston Pops [1993]  FLAC","uid":12961799,"size":357316150,"categoryP":"audio","categoryS":"flac","magnet":"?xt=urn:btih:4515a3e02dc879a5311359e6da24e9330a2a419e&amp;dn=Marches+in+HI-FI+-+Fiedler%2C+Boston+Pops+%5B1993%5D++FLAC&amp;tr=udp%3A%2F%2Ftracker.leechers-paradise.org%3A6969&amp;tr=udp%3A%2F%2Fzer0day.ch%3A1337&amp;tr=udp%3A%2F%2Fopen.demonii.com%3A1337&amp;tr=udp%3A%2F%2Ftracker.coppersurfer.tk%3A6969&amp;tr=udp%3A%2F%2Fexodus.desync.com%3A6969","seeders":1,"leechers":0,"uploader":"keeybee","files":42,"time":1449856707,"description":"Please seed!\r\n\r\nArthur Fiedler &amp; Boston Pops Orchestra - Marches in Hi-Fi\r\nCD 1993\r\n \nhttps://en.wikipedia.org/wiki/Arthur_Fiedler \nhttps://en.wikipedia.org/wiki/Boston_Pops_Orchestra\r\n\r\nWith art work\r\n\r\n01  Verdi: Aida - Grand March\r\n02  Herbert: Babes In Toyland - March Of The Toys\r\n03  Sousa: Semper Fidelis\r\n04  Tchaikovsky: Suite #1 In D, Op. 43 - Marche Miniature\r\n05  Traditional: Yankee Doodle\r\n06  Morse: Up the Street\r\n07  Berlioz: The Damnation Of Faust, Op. 24 - Rakoczy March\r\n08  Rodgers: The King and I, March of the Siamese Children\r\n09  Ippolitov-Ivanov: Caucasian Sketches - Procession Of The Sardar\r\n10  Planquette: Le régiment de Sambre-et-Meuse\r\n11  Beethoven: The Ruins Of Athens, Op. 113, Turkish March\r\n12  Alford: Colonel Bogey\r\n13  Emmett: Dixie\r\n14  Gould: American Salute (When Johnny Comes Marching Home)\r\n15  Gershwin: Strike Up The Band!\r\n16  Mendelssohn: Athalie, Op. 74 - War March of the Priests\r\n17  Sibelius: Karelia Suite, Op.11.III - Alla marcia\r\n18  Rózsa: March of the Charioteers (from 'Ben Hur')\r\n19  Sousa: The Stars and Stripes Forever\r\n \nhttp://www.allmusic.com/album/marches-in-hi-fi-mw0000297199","torrent":{"xt":"urn:btih:4515a3e02dc879a5311359e6da24e9330a2a419e","amp;dn":"Marches+in+HI-FI+-+Fiedler%2C+Boston+Pops+%5B1993%5D++FLAC","amp;tr":["udp%3A%2F%2Ftracker.leechers-paradise.org%3A6969","udp%3A%2F%2Fzer0day.ch%3A1337","udp%3A%2F%2Fopen.demonii.com%3A1337","udp%3A%2F%2Ftracker.coppersurfer.tk%3A6969","udp%3A%2F%2Fexodus.desync.com%3A6969"],"infoHash":"4515a3e02dc879a5311359e6da24e9330a2a419e","infoHashBuffer":{"type":"Buffer","data":[69,21,163,224,45,200,121,165,49,19,89,230,218,36,233,51,10,42,65,158]},"announce":[],"urlList":[]}}