{"title":"AGENTomasz - pierwszy sezon","uid":6788611,"size":3302159141,"categoryP":"audio","categoryS":"sound_clips","magnet":"?xt=urn:btih:4f5ecc5a0d16ce0dacc499d2ff68441d6ad70a29&amp;dn=AGENTomasz+-+pierwszy+sezon&amp;tr=udp%3A%2F%2Ftracker.openbittorrent.com%3A80&amp;tr=udp%3A%2F%2Fopen.demonii.com%3A1337&amp;tr=udp%3A%2F%2Ftracker.coppersurfer.tk%3A6969&amp;tr=udp%3A%2F%2Fexodus.desync.com%3A6969","seeders":1,"leechers":0,"uploader":"AGNTMSZ","files":31,"time":1320186917,"description":"CaÃ…","torrent":{"xt":"urn:btih:4f5ecc5a0d16ce0dacc499d2ff68441d6ad70a29","amp;dn":"AGENTomasz+-+pierwszy+sezon","amp;tr":["udp%3A%2F%2Ftracker.openbittorrent.com%3A80","udp%3A%2F%2Fopen.demonii.com%3A1337","udp%3A%2F%2Ftracker.coppersurfer.tk%3A6969","udp%3A%2F%2Fexodus.desync.com%3A6969"],"infoHash":"4f5ecc5a0d16ce0dacc499d2ff68441d6ad70a29","infoHashBuffer":{"type":"Buffer","data":[79,94,204,90,13,22,206,13,172,196,153,210,255,104,68,29,106,215,10,41]},"announce":[],"urlList":[]}}