{"title":"[BigNaturals] Nicole Banks (Breasty Banks / 05.08.2013)","uid":8451074,"size":534296251,"categoryP":"porn","categoryS":"movies","magnet":"?xt=urn:btih:54e8f5a94ece619d66e9fe8cf8a3b110afa5be35&amp;dn=%5BBigNaturals%5D+Nicole+Banks+%28Breasty+Banks+%2F+05.08.2013%29&amp;tr=udp%3A%2F%2Ftracker.openbittorrent.com%3A80&amp;tr=udp%3A%2F%2Fopen.demonii.com%3A1337&amp;tr=udp%3A%2F%2Ftracker.coppersurfer.tk%3A6969&amp;tr=udp%3A%2F%2Fexodus.desync.com%3A6969","seeders":1,"leechers":0,"uploader":"chkm8te","files":2,"time":1368003916,"description":"[BigNaturals] Nicole Banks (Breasty Banks / 05.08.2013)\n\nNicole modeled a fishnet outfit while waiting for her boyfriend to arrive. She caressed, bounced and pressed her huge melons together. Eventually she unleashed the bazongas from the fishnet that they nicely pressed against and then licked her hard nipples. Nicole's boyfriend arrived just in time to oil, rub and titty fuck her. Soon after smacking his dick on her tits, he stuffed her pretty mouth and then pounded her tight pussy relentlessly. Nicole got her juggs evenly glazed with her man's jizz.\n\nScreens: &lt;a href=&quot;\nhttp://xxxhost.me/viewer.php?file=16ld1eu5y87hq532g0hp.jpg&quot; rel=&quot;nofollow&quot; target=&quot;_NEW&quot;&gt;\nhttp://xxxhost.me/viewer.php?file=16ld1eu5y87hq532g0hp.jpg&lt;/a&gt;\n &lt;a href=&quot;\nhttp://xxxhost.me/viewer.php?file=i3fejtiiuit5jlkstv4i.jpg&quot; rel=&quot;nofollow&quot; target=&quot;_NEW&quot;&gt;\nhttp://xxxhost.me/viewer.php?file=i3fejtiiuit5jlkstv4i.jpg&lt;/a&gt;","torrent":{"xt":"urn:btih:54e8f5a94ece619d66e9fe8cf8a3b110afa5be35","amp;dn":"%5BBigNaturals%5D+Nicole+Banks+%28Breasty+Banks+%2F+05.08.2013%29","amp;tr":["udp%3A%2F%2Ftracker.openbittorrent.com%3A80","udp%3A%2F%2Fopen.demonii.com%3A1337","udp%3A%2F%2Ftracker.coppersurfer.tk%3A6969","udp%3A%2F%2Fexodus.desync.com%3A6969"],"infoHash":"54e8f5a94ece619d66e9fe8cf8a3b110afa5be35","infoHashBuffer":{"type":"Buffer","data":[84,232,245,169,78,206,97,157,102,233,254,140,248,163,177,16,175,165,190,53]},"announce":[],"urlList":[]}}