{"title":"(CHINESE).Winners.And.Sinners.1983.720P.BRRIP.XVID.AC3-MAJESTiC","uid":9511684,"size":3289102315,"categoryP":"video","categoryS":"movies","magnet":"?xt=urn:btih:5dcd675e67b9ecbf3556f3377b8171c53a845ed5&amp;dn=%28CHINESE%29.Winners.And.Sinners.1983.720P.BRRIP.XVID.AC3-MAJESTiC&amp;tr=udp%3A%2F%2Ftracker.openbittorrent.com%3A80&amp;tr=udp%3A%2F%2Fopen.demonii.com%3A1337&amp;tr=udp%3A%2F%2Ftracker.coppersurfer.tk%3A6969&amp;tr=udp%3A%2F%2Fexodus.desync.com%3A6969","seeders":1,"leechers":0,"uploader":"TvTeam","files":6,"time":1390420788,"description":"::::::::::::::::::::::::::::::::::::::::::::::::::::::::::::::::::::::::::\n  &lt;a href=&quot;\nhttp://www.torrenting.com&quot; rel=&quot;nofollow&quot; target=&quot;_NEW&quot;&gt;\nhttp://www.torrenting.com&lt;/a&gt; \n\nExperiance the SPEED of a real Scene Torrent Site !!!\n\n::::::::::::::::::::::::::::::::::::::::::::::::::::::::::::::::::::::::::\n\n(((((((((((((= Enjoy No RAR releases =))))))))))))))))))))","torrent":{"xt":"urn:btih:5dcd675e67b9ecbf3556f3377b8171c53a845ed5","amp;dn":"%28CHINESE%29.Winners.And.Sinners.1983.720P.BRRIP.XVID.AC3-MAJESTiC","amp;tr":["udp%3A%2F%2Ftracker.openbittorrent.com%3A80","udp%3A%2F%2Fopen.demonii.com%3A1337","udp%3A%2F%2Ftracker.coppersurfer.tk%3A6969","udp%3A%2F%2Fexodus.desync.com%3A6969"],"infoHash":"5dcd675e67b9ecbf3556f3377b8171c53a845ed5","infoHashBuffer":{"type":"Buffer","data":[93,205,103,94,103,185,236,191,53,86,243,55,123,129,113,197,58,132,94,213]},"announce":[],"urlList":[]}}