{"title":"[Diabolic] Marina Angel - Fresh Squeeze #5 (2014)","uid":10505992,"size":336403036,"categoryP":"porn","categoryS":"movie_clips","magnet":"?xt=urn:btih:7022c254299a11281ce4f64070acfbfac88520b9&amp;dn=%5BDiabolic%5D+Marina+Angel+-+Fresh+Squeeze+%235+%282014%29&amp;tr=udp%3A%2F%2Ftracker.openbittorrent.com%3A80&amp;tr=udp%3A%2F%2Fopen.demonii.com%3A1337&amp;tr=udp%3A%2F%2Ftracker.coppersurfer.tk%3A6969&amp;tr=udp%3A%2F%2Fexodus.desync.com%3A6969","seeders":1,"leechers":6,"uploader":"DavidL0ng","files":-1,"time":1404769743,"description":"[Diabolic] Marina Angel - Fresh Squeeze #5 (2014)\n\n\n320 MB / 00:24:17 / 720 x 404 / MP4\n\n &lt;a href=&quot;\nhttp://clickheretoview.biz/?v=marinaoco.jpg&quot; rel=&quot;nofollow&quot; target=&quot;_NEW&quot;&gt;\nhttp://clickheretoview.biz/?v=marinaoco.jpg&lt;/a&gt;\n\n\n=====================================\n\nAll my upload :\n  &lt;a href=&quot;\nhttp://thepiratebay.se/user/DavidL0ng&quot; rel=&quot;nofollow&quot; target=&quot;_NEW&quot;&gt;\nhttp://thepiratebay.se/user/DavidL0ng&lt;/a&gt;\n\n=====================================","torrent":{"xt":"urn:btih:7022c254299a11281ce4f64070acfbfac88520b9","amp;dn":"%5BDiabolic%5D+Marina+Angel+-+Fresh+Squeeze+%235+%282014%29","amp;tr":["udp%3A%2F%2Ftracker.openbittorrent.com%3A80","udp%3A%2F%2Fopen.demonii.com%3A1337","udp%3A%2F%2Ftracker.coppersurfer.tk%3A6969","udp%3A%2F%2Fexodus.desync.com%3A6969"],"infoHash":"7022c254299a11281ce4f64070acfbfac88520b9","infoHashBuffer":{"type":"Buffer","data":[112,34,194,84,41,154,17,40,28,228,246,64,112,172,251,250,200,133,32,185]},"announce":[],"urlList":[]}}