{"title":"New Amsterdam 1x03[HDTV][Spanish].avi","uid":4353026,"size":365146112,"categoryP":"video","categoryS":"tv_shows","magnet":"?xt=urn:btih:72707bf187bca2e1bcf2e79c301af2563ced7827&amp;dn=New+Amsterdam+1x03%5BHDTV%5D%5BSpanish%5D.avi&amp;tr=udp%3A%2F%2Ftracker.openbittorrent.com%3A80&amp;tr=udp%3A%2F%2Fopen.demonii.com%3A1337&amp;tr=udp%3A%2F%2Ftracker.coppersurfer.tk%3A6969&amp;tr=udp%3A%2F%2Fexodus.desync.com%3A6969","seeders":1,"leechers":0,"uploader":"webchella","files":1,"time":1219266862,"description":"New Amsterdam 1x03[HDTV][Spanish]","torrent":{"xt":"urn:btih:72707bf187bca2e1bcf2e79c301af2563ced7827","amp;dn":"New+Amsterdam+1x03%5BHDTV%5D%5BSpanish%5D.avi","amp;tr":["udp%3A%2F%2Ftracker.openbittorrent.com%3A80","udp%3A%2F%2Fopen.demonii.com%3A1337","udp%3A%2F%2Ftracker.coppersurfer.tk%3A6969","udp%3A%2F%2Fexodus.desync.com%3A6969"],"infoHash":"72707bf187bca2e1bcf2e79c301af2563ced7827","infoHashBuffer":{"type":"Buffer","data":[114,112,123,241,135,188,162,225,188,242,231,156,48,26,242,86,60,237,120,39]},"announce":[],"urlList":[]}}