{"title":"SIAKOL [PHIL] - TAYO NA SA PARAISO [.MP3]  -=cR@ZylOV3r=-","uid":4477951,"size":44564827,"categoryP":"audio","categoryS":"music","magnet":"?xt=urn:btih:7b51c74b83d35a43b8f051bcd41c6c0590fca3a7&amp;dn=SIAKOL+%5BPHIL%5D+-+TAYO+NA+SA+PARAISO+%5B.MP3%5D++-%3DcR%40ZylOV3r%3D-&amp;tr=udp%3A%2F%2Ftracker.openbittorrent.com%3A80&amp;tr=udp%3A%2F%2Fopen.demonii.com%3A1337&amp;tr=udp%3A%2F%2Ftracker.coppersurfer.tk%3A6969&amp;tr=udp%3A%2F%2Fexodus.desync.com%3A6969","seeders":2,"leechers":0,"uploader":"crazylov3r","files":14,"time":1225427060,"description":"################################################################################\n################################################################################\n######################          FILIPINO PRIDE            ######################\n################################################################################\n############****##****###**##*******#***#**###****#**##**#***##****#############\n###*****###**##**#**#**#***####**##****##**##**##****#**#****##**#**###*****####\n###########**#####****##****###**###**###**##**##**#****###**##****#############\n#*******###**##**#****#*****##**####**###**##**##**#***##**#**#****####********#\n############****##**#****##*******##**###****#****###**###***##**#**############\n################################################################################\n#######                    &lt;a class=&quot;__cf_email__&quot; href=&quot;/cdn-cgi/l/email-protection&quot; data-cfemail=&quot;73302132292a3f3c2540214706332a323b3c3c5d303c3e&quot;&gt;[email&amp;#160;protected]&lt;/a&gt;&lt;script cf-hash='f9e31' type=&quot;text/javascript&quot;&gt;\n/* &lt;![CDATA[ */!function(){try{var t=&quot;currentScript&quot;in document?document.currentScript:function(){for(var t=document.getElementsByTagName(&quot;script&quot;),e=t.length;e--;)if(t[e].getAttribute(&quot;cf-hash&quot;))return t[e]}();if(t&amp;&amp;t.previousSibling){var e,r,n,i,c=t.previousSibling,a=c.getAttribute(&quot;data-cfemail&quot;);if(a){for(e=&quot;&quot;,r=parseInt(a.substr(0,2),16),n=2;a.length-n;n+=2)i=parseInt(a.substr(n,2),16)^r,e+=String.fromCharCode(i);e=document.createTextNode(e),c.parentNode.replaceChild(e,c)}}}catch(u){}}();/* ]]&gt; */&lt;/script&gt;                        #######\n################################################################################\n################################################################################\n################################################################################\n\t\t\t\t\t\t                 MABUHAY!2008*#*\n\n\n WARNING:PROMOTIONAL USE ONLY &quot;HAVE YOUR ORIGINAL COPY TO SUPPORT THE INDUSTRY&quot;\t\n\n      ***************************************\n     *****************************************\n    *******************************************\n   ****************** MUSIC ******************** \n   ********************************************* \n    *******************************************\n     *****************************************\n           RIPPED BY:  -= cR@ZylOV3r =-\t\n\t\n\t\n\n\tARTIST: \tSIAKOL\n\tALBUM:\t\tTAYO NA SA PARAISO\n\tLANGUAGE: \tTAGALOG\n\tCOUNTRY:\tPHILIPPINES\n\tGENRE: \t\tROCK\n\tFILES: \t        . MP3\n\tMEDIA:\t\tWINAMP V 5.54\n        MUSIC CONTENTS : \n\n1 Lagim\n2 Biyaheng Impiyerno\n3 Alaws Arep\n4 Kanto\n5 Salot\n6 Lakas-Tama\n7 Peksman\n8 Bakit Ba?\n9 Sistemang Bulok\n10 Bato-Bato Sa Langit\n11 A...N.P...\n12 Aso\n\n\n################################################################################\n################################################################################\n***********************************PLEASE READ**********************************\n##                                                                            ##\n##     VISIT MY PIRATE BAY ACCOUNT : http://thepiratebay.se/user/crazylov3r/ ##\n##                                                                            ##\n##      PLEASE SEED AFTER DOWNLOADING HAVE YOUR SHARE IN THE TORRENT WORLD    ##\n##                                                                            ##\n##               DOWNLOAD TORRENTS FROM TRUSTED UPLOADERS ONLY                ##\n##                                                                            ##\n##        TO BE SURE OF VIRUS FREE, SCAN TORRENTS BEFORE DOWNLOADING IT       ##\n##                                                                            ##\n##                VIRUS FREE TORRENT BY:  -=cR@ZylOV3r=-                      ##\n##\t\t\t\t\t\t\t\t\t      ##\n##\t\t\t&quot;NOW ACCEPTING REQUEST&quot;\t\t\t\t      ##\n##\t\t\t\t\t\t\t\t\t      ##\n################################################################################\n################################################################################","torrent":{"xt":"urn:btih:7b51c74b83d35a43b8f051bcd41c6c0590fca3a7","amp;dn":"SIAKOL+%5BPHIL%5D+-+TAYO+NA+SA+PARAISO+%5B.MP3%5D++-%3DcR%40ZylOV3r%3D-","amp;tr":["udp%3A%2F%2Ftracker.openbittorrent.com%3A80","udp%3A%2F%2Fopen.demonii.com%3A1337","udp%3A%2F%2Ftracker.coppersurfer.tk%3A6969","udp%3A%2F%2Fexodus.desync.com%3A6969"],"infoHash":"7b51c74b83d35a43b8f051bcd41c6c0590fca3a7","infoHashBuffer":{"type":"Buffer","data":[123,81,199,75,131,211,90,67,184,240,81,188,212,28,108,5,144,252,163,167]},"announce":[],"urlList":[]}}