{"title":"NHK Tsukiji Worlds Largest Fish Market The Incredible Hands x264","uid":11356676,"size":1716843301,"categoryP":"video","categoryS":"hd___tv_shows","magnet":"?xt=urn:btih:7ffd45eab6c9c757339a01acd4b356e18251ce67&amp;dn=NHK+Tsukiji+Worlds+Largest+Fish+Market+The+Incredible+Hands+x264&amp;tr=udp%3A%2F%2Ftracker.openbittorrent.com%3A80&amp;tr=udp%3A%2F%2Fopen.demonii.com%3A1337&amp;tr=udp%3A%2F%2Ftracker.coppersurfer.tk%3A6969&amp;tr=udp%3A%2F%2Fexodus.desync.com%3A6969","seeders":1,"leechers":1,"uploader":"MVGroup","files":-1,"time":1414952347,"description":"The Incredible Hands\n\nCulture Documentary hosted by Chris Kent, published by NHK broadcasted as part of NHK Tsukiji :World's Largest Fish Market series in 2009 - English narration\n\n\nInformation\n------------------------------\n\n)t is not just an ordinary fish market. It is the BIGGEST in the world with a traffic of 100,000 people going in and out of 850 stalls. 50,000 tons of fish is traded daily with hundreds of millions of dollars changing hands. Its famous auctions have attracted millions of tourists worldwide. But what lies beneath the surface of this amazing market?\nThis episode is a visual feast of never -before -filmed sequences on how a 300-kg tuna is cut, and all the the unique skills of the fishmongers and the myriad varieties of seafood available\n\nScreenshots\n------------------------------ &lt;a href=&quot;\nhttp://image.bayimg.com/0a40bdd9738129ad097ca9450cd6eedae99130b3.jpg&quot; rel=&quot;nofollow&quot; target=&quot;_NEW&quot;&gt;\nhttp://image.bayimg.com/0a40bdd9738129ad097ca9450cd6eedae99130b3.jpg&lt;/a&gt; &lt;a href=&quot;\nhttp://image.bayimg.com/8a9c4dc402fe6e3d88ae1ff14aeb03d0164f3007.jpg&quot; rel=&quot;nofollow&quot; target=&quot;_NEW&quot;&gt;\nhttp://image.bayimg.com/8a9c4dc402fe6e3d88ae1ff14aeb03d0164f3007.jpg&lt;/a&gt; &lt;a href=&quot;\nhttp://image.bayimg.com/54a834a5dd907df2a39fc0e7bba09ba957ee10a9.jpg&quot; rel=&quot;nofollow&quot; target=&quot;_NEW&quot;&gt;\nhttp://image.bayimg.com/54a834a5dd907df2a39fc0e7bba09ba957ee10a9.jpg&lt;/a&gt; &lt;a href=&quot;\nhttp://image.bayimg.com/b2630e0c27017476b43990a042f2056ec91c774d.jpg&quot; rel=&quot;nofollow&quot; target=&quot;_NEW&quot;&gt;\nhttp://image.bayimg.com/b2630e0c27017476b43990a042f2056ec91c774d.jpg&lt;/a&gt; &lt;a href=&quot;\nhttp://image.bayimg.com/fd10bc4e1928c59583d556a9afa1453933783b33.jpg&quot; rel=&quot;nofollow&quot; target=&quot;_NEW&quot;&gt;\nhttp://image.bayimg.com/fd10bc4e1928c59583d556a9afa1453933783b33.jpg&lt;/a&gt; &lt;a href=&quot;\nhttp://image.bayimg.com/94e8ed6ab315cb95f984da239e21d3be4f5e78be.jpg&quot; rel=&quot;nofollow&quot; target=&quot;_NEW&quot;&gt;\nhttp://image.bayimg.com/94e8ed6ab315cb95f984da239e21d3be4f5e78be.jpg&lt;/a&gt; \n\nTechnical Specs\n------------------------------\n\nVideo Codec: x264 ,AVC-1\nVideo Bitrate: CRF 20\nVideo Resolution: 1280x720\nVideo Aspect Ratio: 16:9\nAudio Codec: AC3\nAudio BitRate: 192 kbps\nAudio Streams: 2.0\nAudio Languages: English\nRunTime Per Part: 48 min\nNumber Of Parts: 1\nPart Size: 1.59 GB\nRipped by Hukumuzuku\n\nLinks\n------------------------------\n\n1)  Related Documentaries &lt;a href=&quot;\nhttp://docuwiki.net/?title=The%20London%20Markets&quot; rel=&quot;nofollow&quot; target=&quot;_NEW&quot;&gt;\nhttp://docuwiki.net/?title=The%20London%20Markets&lt;/a&gt; &lt;a href=&quot;\nhttp://docuwiki.net/?title=A%20Flea%20Market%20Documentary&quot; rel=&quot;nofollow&quot; target=&quot;_NEW&quot;&gt;\nhttp://docuwiki.net/?title=A%20Flea%20Market%20Documentary&lt;/a&gt;\n\n2)  ed2k Links \n\n &lt;a href=&quot;\nhttp://docuwiki.net/?title=User%3AHukumuzuku&quot; rel=&quot;nofollow&quot; target=&quot;_NEW&quot;&gt;\nhttp://docuwiki.net/?title=User%3AHukumuzuku&lt;/a&gt;\n\nSource: &lt;a href=&quot;\nhttp://docuwiki.net/index.php?title=The_Incredible_Hands&quot; rel=&quot;nofollow&quot; target=&quot;_NEW&quot;&gt;\nhttp://docuwiki.net/index.php?title=The_Incredible_Hands&lt;/a&gt;","torrent":{"xt":"urn:btih:7ffd45eab6c9c757339a01acd4b356e18251ce67","amp;dn":"NHK+Tsukiji+Worlds+Largest+Fish+Market+The+Incredible+Hands+x264","amp;tr":["udp%3A%2F%2Ftracker.openbittorrent.com%3A80","udp%3A%2F%2Fopen.demonii.com%3A1337","udp%3A%2F%2Ftracker.coppersurfer.tk%3A6969","udp%3A%2F%2Fexodus.desync.com%3A6969"],"infoHash":"7ffd45eab6c9c757339a01acd4b356e18251ce67","infoHashBuffer":{"type":"Buffer","data":[127,253,69,234,182,201,199,87,51,154,1,172,212,179,86,225,130,81,206,103]},"announce":[],"urlList":[]}}