{"title":"Bow To The King-EP 2013","uid":9407496,"size":30851224,"categoryP":"audio","categoryS":"music","magnet":"?xt=urn:btih:a51b02f90e73e122aab8c3c3dba9ea5fd2c3bfa1&amp;dn=Bow+To+The+King-EP+2013&amp;tr=udp%3A%2F%2Ftracker.openbittorrent.com%3A80&amp;tr=udp%3A%2F%2Fopen.demonii.com%3A1337&amp;tr=udp%3A%2F%2Ftracker.coppersurfer.tk%3A6969&amp;tr=udp%3A%2F%2Fexodus.desync.com%3A6969","seeders":1,"leechers":0,"uploader":"rouvale","files":5,"time":1388197186,"description":"Bow To The King: EP &quot;To A Future Yet Unknown&quot; 2013\n\n1. And Tonight, We Celebrate! 03:06\n\n2.of corruption 03:31\n\n3.To A Future Yet Unknown 04:26\n\n4.Until my last drop: 04:03\n\n-------------------------------\n\nLocation: Greece\n\nGenre: Metalcore/Pop Punk/Happycore\n\nEP Released:28/09/2013\n \n\n","torrent":{"xt":"urn:btih:a51b02f90e73e122aab8c3c3dba9ea5fd2c3bfa1","amp;dn":"Bow+To+The+King-EP+2013","amp;tr":["udp%3A%2F%2Ftracker.openbittorrent.com%3A80","udp%3A%2F%2Fopen.demonii.com%3A1337","udp%3A%2F%2Ftracker.coppersurfer.tk%3A6969","udp%3A%2F%2Fexodus.desync.com%3A6969"],"infoHash":"a51b02f90e73e122aab8c3c3dba9ea5fd2c3bfa1","infoHashBuffer":{"type":"Buffer","data":[165,27,2,249,14,115,225,34,170,184,195,195,219,169,234,95,210,195,191,161]},"announce":[],"urlList":[]}}