{"title":"Classical Hits - J.S. Bach","uid":4375556,"size":90134342,"categoryP":"audio","categoryS":"music","magnet":"?xt=urn:btih:c9ae4af94bcdb84ab6e8d5b34c9dc4e2baa9c29b&amp;dn=Classical+Hits+-+J.S.+Bach&amp;tr=udp%3A%2F%2Ftracker.openbittorrent.com%3A80&amp;tr=udp%3A%2F%2Fopen.demonii.com%3A1337&amp;tr=udp%3A%2F%2Ftracker.coppersurfer.tk%3A6969&amp;tr=udp%3A%2F%2Fexodus.desync.com%3A6969","seeders":1,"leechers":0,"uploader":"nightissuchproximity","files":13,"time":1220389638,"description":"This guy was even more popular than Slade.   That reminds me...my next upload will be Slade.   For those of you that remember the nights in...never mind.\n   I saw Slade live at Reading.   Just before I got lifted for possession of cannabis.   I wish one of you looking at this text right now knew what the shit I&amp;#039;m talking about.   ","torrent":{"xt":"urn:btih:c9ae4af94bcdb84ab6e8d5b34c9dc4e2baa9c29b","amp;dn":"Classical+Hits+-+J.S.+Bach","amp;tr":["udp%3A%2F%2Ftracker.openbittorrent.com%3A80","udp%3A%2F%2Fopen.demonii.com%3A1337","udp%3A%2F%2Ftracker.coppersurfer.tk%3A6969","udp%3A%2F%2Fexodus.desync.com%3A6969"],"infoHash":"c9ae4af94bcdb84ab6e8d5b34c9dc4e2baa9c29b","infoHashBuffer":{"type":"Buffer","data":[201,174,74,249,75,205,184,74,182,232,213,179,76,157,196,226,186,169,194,155]},"announce":[],"urlList":[]}}