{"title":"Justin Timberlake - The 20-20 Experience (Deluxe Edition) (2013)","uid":8955649,"size":115824010,"categoryP":"audio","categoryS":"music","magnet":"?xt=urn:btih:d3d39725007c745564f4ef46b4637e5665150c79&amp;dn=Justin+Timberlake+-+The+20-20+Experience+%28Deluxe+Edition%29+%282013%29&amp;tr=udp%3A%2F%2Ftracker.openbittorrent.com%3A80&amp;tr=udp%3A%2F%2Fopen.demonii.com%3A1337&amp;tr=udp%3A%2F%2Ftracker.coppersurfer.tk%3A6969&amp;tr=udp%3A%2F%2Fexodus.desync.com%3A6969","seeders":1,"leechers":0,"uploader":"420weedman","files":13,"time":1379987223,"description":"1\tPusher Love Girl\t8:02\n2\tSuit &amp; Tie\t5:26\n3\tDon't Hold the Wall\t7:11\n4\tStrawberry Bubblegum\t8:00\n5\tTunnel Vision\t6:47\n6\tSpaceship Coupe\t7:17\n7\tThat Girl\t4:48\n8\tLet the Groove Get In\t7:12\n9\tMirrors\t8:06\n10\tBlue Ocean Floor\t7:19","torrent":{"xt":"urn:btih:d3d39725007c745564f4ef46b4637e5665150c79","amp;dn":"Justin+Timberlake+-+The+20-20+Experience+%28Deluxe+Edition%29+%282013%29","amp;tr":["udp%3A%2F%2Ftracker.openbittorrent.com%3A80","udp%3A%2F%2Fopen.demonii.com%3A1337","udp%3A%2F%2Ftracker.coppersurfer.tk%3A6969","udp%3A%2F%2Fexodus.desync.com%3A6969"],"infoHash":"d3d39725007c745564f4ef46b4637e5665150c79","infoHashBuffer":{"type":"Buffer","data":[211,211,151,37,0,124,116,85,100,244,239,70,180,99,126,86,101,21,12,121]},"announce":[],"urlList":[]}}