{"title":"The Twilight Zone - A Short Drink From A Certain Fountain","uid":11037190,"size":169736192,"categoryP":"video","categoryS":"tv_shows","magnet":"?xt=urn:btih:e0e3abd7f16b8c7b532945274c91b8bebd4fb0c3&amp;dn=The+Twilight+Zone+-+A+Short+Drink+From+A+Certain+Fountain&amp;tr=udp%3A%2F%2Ftracker.openbittorrent.com%3A80&amp;tr=udp%3A%2F%2Fopen.demonii.com%3A1337&amp;tr=udp%3A%2F%2Ftracker.coppersurfer.tk%3A6969&amp;tr=udp%3A%2F%2Fexodus.desync.com%3A6969","seeders":1,"leechers":0,"uploader":"Mooseleg8","files":-1,"time":1410808039,"description":"Harmon Gordon is now quite elderly but is married to Flora, an attractive woman some 40 years younger than him. She's something of a gold digger and is now quite bored with her marriage. Harmon turns to his younger brother Raymond, a medical doctor who has been experimenting with cellular regeneration. Raymond's experiments to date have been on lab animals and he's reluctant to help Harmon as he has no idea what effect his youth serum might have on him. In the end, he administers his serum and by the next day Harmon is a new man, so to speak.","torrent":{"xt":"urn:btih:e0e3abd7f16b8c7b532945274c91b8bebd4fb0c3","amp;dn":"The+Twilight+Zone+-+A+Short+Drink+From+A+Certain+Fountain","amp;tr":["udp%3A%2F%2Ftracker.openbittorrent.com%3A80","udp%3A%2F%2Fopen.demonii.com%3A1337","udp%3A%2F%2Ftracker.coppersurfer.tk%3A6969","udp%3A%2F%2Fexodus.desync.com%3A6969"],"infoHash":"e0e3abd7f16b8c7b532945274c91b8bebd4fb0c3","infoHashBuffer":{"type":"Buffer","data":[224,227,171,215,241,107,140,123,83,41,69,39,76,145,184,190,189,79,176,195]},"announce":[],"urlList":[]}}