{"title":"iPod Porn Movies [MP4] - Bondage Dolls 2","uid":4521475,"size":17961266,"categoryP":"porn","categoryS":"movie_clips","magnet":"?xt=urn:btih:e13953ac5f79e1431dad2788e8c6b077efc4a62a&amp;dn=iPod+Porn+Movies+%5BMP4%5D+-+Bondage+Dolls+2&amp;tr=udp%3A%2F%2Ftracker.openbittorrent.com%3A80&amp;tr=udp%3A%2F%2Fopen.demonii.com%3A1337&amp;tr=udp%3A%2F%2Ftracker.coppersurfer.tk%3A6969&amp;tr=udp%3A%2F%2Fexodus.desync.com%3A6969","seeders":1,"leechers":0,"uploader":"bombmobile","files":-1,"time":1227181971,"description":"Title:  \tBondage Dolls 2\nStudio: \tBizarre Studios\n\nWebSite:       &lt;a href=&quot; http://bombmobile.com/mobile-porn-movie/bondage-dolls-2&quot; rel=&quot;nofollow&quot; target=&quot;_NEW&quot;&gt; http://bombmobile.com/mobile-porn-movie/bondage-dolls-2&lt;/a&gt;\n\nActors: \t\n\n    * Brittany Sky\n    * Nicole Sheridan\n    * Paige Richards\n    * Persephone\n    * Shelby Stevens\n    * Tanya Danielle\n\nNiches: \t\n\n    * Bondage\n    * Fetish\n\nDescription: \t\nAre you afraid, are you very afraid or just shaking with anticipation? \nOne of the toughest Doms punishes their way to pleasure. \nThe cat o' nine tails plays a big part in this video of torture \nas well as other implements of pain and of course pleasure. \nThe slaves are made to endure punishment beyond cruelty!","torrent":{"xt":"urn:btih:e13953ac5f79e1431dad2788e8c6b077efc4a62a","amp;dn":"iPod+Porn+Movies+%5BMP4%5D+-+Bondage+Dolls+2","amp;tr":["udp%3A%2F%2Ftracker.openbittorrent.com%3A80","udp%3A%2F%2Fopen.demonii.com%3A1337","udp%3A%2F%2Ftracker.coppersurfer.tk%3A6969","udp%3A%2F%2Fexodus.desync.com%3A6969"],"infoHash":"e13953ac5f79e1431dad2788e8c6b077efc4a62a","infoHashBuffer":{"type":"Buffer","data":[225,57,83,172,95,121,225,67,29,173,39,136,232,198,176,119,239,196,166,42]},"announce":[],"urlList":[]}}