{"title":"The Slutty Girls At School #2 (Split Scenes)","uid":8742152,"size":850617877,"categoryP":"porn","categoryS":"movies","magnet":"?xt=urn:btih:e9f44c5137763605329ab70916d8e584bf7d2f8c&amp;dn=The+Slutty+Girls+At+School+%232+%28Split+Scenes%29&amp;tr=udp%3A%2F%2Ftracker.openbittorrent.com%3A80&amp;tr=udp%3A%2F%2Fopen.demonii.com%3A1337&amp;tr=udp%3A%2F%2Ftracker.coppersurfer.tk%3A6969&amp;tr=udp%3A%2F%2Fexodus.desync.com%3A6969","seeders":1,"leechers":1,"uploader":"chkm8te","files":4,"time":1374816931,"description":"The Slutty Girls At School #2 (Split Scenes)\n\nKatie Gold, Brittney Starr, Dawn, Joleen Love\n\nThese are the girls you always wanted to bang!\nThe faces have changed but the slutty attitude hasn't! These horny students are ready to drop their panties at the first sign of a rock hard cock! All finally legal babes!\n\nScreens: &lt;a href=&quot;\nhttp://xxxces.com/viewer.php?file=m428v4onjvofgarh2u0l.jpg&quot; rel=&quot;nofollow&quot; target=&quot;_NEW&quot;&gt;\nhttp://xxxces.com/viewer.php?file=m428v4onjvofgarh2u0l.jpg&lt;/a&gt;\n &lt;a href=&quot;\nhttp://xxxces.com/viewer.php?file=n2j10fdku6rq6dof034u.jpg&quot; rel=&quot;nofollow&quot; target=&quot;_NEW&quot;&gt;\nhttp://xxxces.com/viewer.php?file=n2j10fdku6rq6dof034u.jpg&lt;/a&gt;","torrent":{"xt":"urn:btih:e9f44c5137763605329ab70916d8e584bf7d2f8c","amp;dn":"The+Slutty+Girls+At+School+%232+%28Split+Scenes%29","amp;tr":["udp%3A%2F%2Ftracker.openbittorrent.com%3A80","udp%3A%2F%2Fopen.demonii.com%3A1337","udp%3A%2F%2Ftracker.coppersurfer.tk%3A6969","udp%3A%2F%2Fexodus.desync.com%3A6969"],"infoHash":"e9f44c5137763605329ab70916d8e584bf7d2f8c","infoHashBuffer":{"type":"Buffer","data":[233,244,76,81,55,118,54,5,50,154,183,9,22,216,229,132,191,125,47,140]},"announce":[],"urlList":[]}}