{"title":"Markus Schulz - Global DJ Broadcast (2014-05-29) (Inspiron)","uid":10316545,"size":229490428,"categoryP":"audio","categoryS":"music","magnet":"?xt=urn:btih:f035839cd24ca9b31f0765160f2292d5be509fa1&amp;dn=Markus+Schulz+-+Global+DJ+Broadcast+%282014-05-29%29+%28Inspiron%29&amp;tr=udp%3A%2F%2Ftracker.openbittorrent.com%3A80&amp;tr=udp%3A%2F%2Fopen.demonii.com%3A1337&amp;tr=udp%3A%2F%2Ftracker.coppersurfer.tk%3A6969&amp;tr=udp%3A%2F%2Fexodus.desync.com%3A6969","seeders":1,"leechers":0,"uploader":"-inspiron-","files":-1,"time":1402249854,"description":"=======================================================\nSite: &lt;a href=&quot; http://inspiron-trance.com&quot; rel=&quot;nofollow&quot; target=&quot;_NEW&quot;&gt; http://inspiron-trance.com&lt;/a&gt;\n=======================================================\n\n\n=======================================================\nF B Page: Inspiron Trance \n=======================================================\n\n\n=======================================================\nTWITTER : inspiron22\n=======================================================\t\n\n\n\nTracklist:\n\n\n\n\nMarkus Schulz\nGareth Emery - Entrada [Garuda]\nVicetone - Ensemble [Doorn]\nRex Mundi - Macchina [Coldharbour]\nMarkus Schulz Feat. Lady Vee - Erase You [Armada]\nCosmic Gate &amp; KhoMha - Tormenta [Armada]\nX-Cite - Highway\nArkham Knights - Tomorrow's World [Interstate]\nFaruk Sabanci &amp; Yilmaz Altanhan - Eighties 2014 [AVA]\nGlobal Selection: Markus Schulz Pres. Dakota - CLXXV [Coldharbour]\nGal Abutbul &amp; First Effect - Intruder [Beat Service]\nMatt Chowski vs Ward Til &amp; Lee Campbell - Ambush (Purple Stories Remix) [Silver Waves]\nJohan Gielen vs Virtual Vault - Blue Fire (Markus Schulz Big Room Reconstruction) [High Contrast]\nElevation - Stadium Control [Coldharbour]\nClassic Of The Week: Above &amp; Beyond &amp; Andy Moor - Air For Life (Markus Schulz Big Room Reconstruction) [Anjunabeats]\nWellenrausch\nLen Faki - Kraft Und Licht (Wellenrausch Dark Matter Bootleg) [Ostgut Ton]\nWellenrausch - Rivers Deep (Wellenrausch Deep Matter Mix) [Afterglow]\nWellenrausch - Dream Within A Dream\nWellenrausch - These Moments\nWellenrausch - City In Flame\nMarkus Schulz\nJudah Feat. Kailin - This Moment [AVA]\nNemphirex - Ireland [Groovenight]\nHarry Romero - Rapture [X]\n16BL (16 Bit Lolitas) - From Far Away [Anjunadeep]\nBlood Groove &amp; Kikis vs LTN - Both (Soarsweep Intelligent Remix) [Silk Digital]\n\n\n\n\nEnjoy\n(Inspiron)","torrent":{"xt":"urn:btih:f035839cd24ca9b31f0765160f2292d5be509fa1","amp;dn":"Markus+Schulz+-+Global+DJ+Broadcast+%282014-05-29%29+%28Inspiron%29","amp;tr":["udp%3A%2F%2Ftracker.openbittorrent.com%3A80","udp%3A%2F%2Fopen.demonii.com%3A1337","udp%3A%2F%2Ftracker.coppersurfer.tk%3A6969","udp%3A%2F%2Fexodus.desync.com%3A6969"],"infoHash":"f035839cd24ca9b31f0765160f2292d5be509fa1","infoHashBuffer":{"type":"Buffer","data":[240,53,131,156,210,76,169,179,31,7,101,22,15,34,146,213,190,80,159,161]},"announce":[],"urlList":[]}}