{"title":"Bb Future 12 Mix","uid":7212552,"size":106801122,"categoryP":"audio","categoryS":"music","magnet":"?xt=urn:btih:fc3da3f567c57d2be2fd86507c9fde408bb24c74&amp;dn=Bb+Future+12+Mix&amp;tr=udp%3A%2F%2Ftracker.openbittorrent.com%3A80&amp;tr=udp%3A%2F%2Fopen.demonii.com%3A1337&amp;tr=udp%3A%2F%2Ftracker.coppersurfer.tk%3A6969&amp;tr=udp%3A%2F%2Fexodus.desync.com%3A6969","seeders":1,"leechers":0,"uploader":"bbry","files":14,"time":1335288244,"description":"This is a mix I made last month for Future 2012, packed with my favourites from Swedish House Mafia :)  Enjoy.\n\nTracklist:\n1. Morgan Page and Sultan - In The Air Feat. Angela McCluskey\n2. Dirty South &amp; Those Usual Suspects - Walking Alone Feat Erik Hecht\n3. Tim Mason - The Moment (Steve Angello Edit)\n4. Knife Party - Antidote\n5. Dirty South &amp; Thomas Gold Feat. Kate Elsworth - Alive (Bb Bootleg)\n6. Avicii - Levels (Bb Bootleg)\n7. Michael Woods vs Nero vs Calvin Harris - Bullet Promises (Bb Bootleg)\n8. Swedish House Mafia - Greyhound\n9. Sandro Silva &amp; Quitino - Epic (Original Mix)\n10. Sebastian Ingrosso &amp; Alesso Feat. Ryan Tedder - Calling (Bb Bootleg)\n11. Knife Party - Internet Friends (Bb Edit)\n12. Ivan Gough &amp; Feenixpawl feat. Georgi Kay - In My Mind (Axwell Mix)\n13. Coldplay - Fix You (Alesso &amp; Swedish House Mafia Remix)\n14. Nadia Ali - Pressure Feat Starkillers &amp; Alex Kenji (Alesso Remix)","torrent":{"xt":"urn:btih:fc3da3f567c57d2be2fd86507c9fde408bb24c74","amp;dn":"Bb+Future+12+Mix","amp;tr":["udp%3A%2F%2Ftracker.openbittorrent.com%3A80","udp%3A%2F%2Fopen.demonii.com%3A1337","udp%3A%2F%2Ftracker.coppersurfer.tk%3A6969","udp%3A%2F%2Fexodus.desync.com%3A6969"],"infoHash":"fc3da3f567c57d2be2fd86507c9fde408bb24c74","infoHashBuffer":{"type":"Buffer","data":[252,61,163,245,103,197,125,43,226,253,134,80,124,159,222,64,139,178,76,116]},"announce":[],"urlList":[]}}